MANIFEST.in
README.md
setup.py
src/django_kenny.egg-info/PKG-INFO
src/django_kenny.egg-info/SOURCES.txt
src/django_kenny.egg-info/dependency_links.txt
src/django_kenny.egg-info/not-zip-safe
src/django_kenny.egg-info/top_level.txt
src/kenny/__init__.py
src/kenny/admin.py
src/kenny/models.py
src/kenny/tests.py
src/kenny/views.py
src/kenny/migrations/__init__.py