Metadata-Version: 1.1
Name: django-kenny
Version: 0.1.0
Summary: An extremely simple dynamic TemplateView for django
Home-page: UNKNOWN
Author: Tomas Neme
Author-email: lacrymology@gmail.com
License: MIT
Keywords: django generic-views
Platform: UNKNOWN
Classifier: Development Status :: 4 - Beta
Classifier: Topic :: Utilities
Classifier: License :: OSI Approved :: MIT License
